secretrandom/__init__.py
secretrandom/main.py
secretrandom-2.4.dist-info/licenses/LICENSE
secretrandom-2.4.dist-info/METADATA
secretrandom-2.4.dist-info/WHEEL
secretrandom-2.4.dist-info/top_level.txt
secretrandom-2.4.dist-info/RECORD
