Metadata-Version: 2.4
Name: secretrandom
Version: 2.4
Summary: Unpredictable cryptographic random number & data generation (random + secrets module combined).
Author-email: dUhEnC-39 <albeback01@gmail.com>
License-Expression: MIT
Requires-Python: >=3.11
License-File: LICENSE
Dynamic: license-file
